kdbai_client/__init__.py
kdbai_client/api.py
kdbai_client/constants.py
kdbai_client/database.py
kdbai_client/database_rest.py
kdbai_client/kdbai_exception.py
kdbai_client/session.py
kdbai_client/session_rest.py
kdbai_client/table.py
kdbai_client/table_rest.py
kdbai_client/utils.py
kdbai_client/version.py
kdbai_client/rerankers/CohereReranker.py
kdbai_client/rerankers/JinaAIReranker.py
kdbai_client/rerankers/VoyageAIReranker.py
kdbai_client/rerankers/__init__.py
kdbai_client/rerankers/base.py
kdbai_client-1.7.0.dist-info/licenses/LICENSE.txt
kdbai_client-1.7.0.dist-info/METADATA
kdbai_client-1.7.0.dist-info/WHEEL
kdbai_client-1.7.0.dist-info/top_level.txt
kdbai_client-1.7.0.dist-info/RECORD
