Metadata-Version: 2.4
Name: kdbai-client
Version: 1.7.0
Summary: KDB.AI Client for Python
Author-email: KX AI Team <ai@kx.com>
License-Expression: Apache-2.0
Classifier: Environment :: Console
Classifier: Environment :: Other Environment
Classifier: Framework :: Flake8
Classifier: Framework :: Pytest
Classifier: Intended Audience :: Developers
Classifier: Intended Audience :: Financial and Insurance Industry
Classifier: Intended Audience :: Healthcare Industry
Classifier: Intended Audience :: Information Technology
Classifier: Intended Audience :: Manufacturing
Classifier: Intended Audience :: Other Audience
Classifier: Intended Audience :: Science/Research
Classifier: Intended Audience :: Telecommunications Industry
Classifier: Operating System :: MacOS
Classifier: Operating System :: Microsoft :: Windows
Classifier: Operating System :: POSIX :: Linux
Classifier: Programming Language :: C
Classifier: Programming Language :: Cython
Classifier: Programming Language :: Other
Classifier: Programming Language :: Other Scripting Engines
Classifier: Programming Language :: Python :: 3.9
Classifier: Programming Language :: Python :: 3.10
Classifier: Programming Language :: Python :: 3.11
Classifier: Programming Language :: Python :: 3 :: Only
Classifier: Programming Language :: Python :: Implementation :: CPython
Classifier: Typing :: Typed
Requires-Python: <3.13,>=3.9
License-File: LICENSE.txt
Requires-Dist: cohere>=5.9.4
Requires-Dist: packaging>=20.9
Requires-Dist: pandas>=1.5.0; python_version < "3.12"
Requires-Dist: pandas>=2.1.1; python_version == "3.12"
Requires-Dist: pykx>=2.1.1; python_version < "3.12"
Requires-Dist: pykx>=2.4.1; python_version == "3.12"
Requires-Dist: requests>=2.32.3
Requires-Dist: voyageai>=0.2.3
Dynamic: license-file
